{
  "report_metadata": {
    "generated_at": "2026-02-10T00:42:05.063388+00:00",
    "report_date": "2026-02-10",
    "version": "1.0",
    "methodology": "Weighted macro factor scoring"
  },
  "macro_environment": {
    "fed_stance": {
      "score": 0,
      "description": "Neutral (75% prob hold)"
    },
    "real_yields": {
      "score": 1,
      "description": "Rising (2.38%)"
    },
    "vix": {
      "score": 1,
      "description": "Falling (17.35)"
    },
    "dxy": {
      "score": 1,
      "description": "Falling (96.87)"
    },
    "growth": {
      "score": 0,
      "description": "Stable (GDPNow 4.2%)"
    },
    "credit_spreads": {
      "score": 1,
      "description": "Narrowing (2.87%)"
    },
    "curve_2s10s": {
      "score": 1,
      "description": "Steepening (0.74%)"
    },
    "sox": {
      "score": 1,
      "description": "Rising (+1.42%)"
    },
    "move": {
      "score": 1,
      "description": "Falling (62.74)"
    },
    "copper": {
      "score": 0,
      "description": "Flat (mixed)"
    },
    "oil_inventories": {
      "score": 1,
      "description": "Draw (-3.5M bbl)"
    },
    "oil_supply": {
      "score": 0,
      "description": "Neutral"
    },
    "gold_etf_flows": {
      "score": 1,
      "description": "Inflows ($19B)"
    },
    "geopolitical_risk": {
      "score": 1,
      "description": "Rising"
    },
    "ecb_stance": {
      "score": 0,
      "description": "Neutral hold"
    },
    "rba_stance": {
      "score": 1,
      "description": "Hawkish (+25bp)"
    },
    "boj_stance": {
      "score": 0,
      "description": "Neutral hold"
    },
    "china_growth": {
      "score": -1,
      "description": "Slowing (PMI 49.3)"
    }
  },
  "instruments": {
    "ES": {
      "name": "E-mini S&P 500",
      "bias_score": 7.06,
      "raw_bias": 0.706,
      "bias_direction": "BULLISH",
      "conviction": "HIGH",
      "factor_contributions": {
        "fed_stance": {
          "weight": 3.0,
          "score": 0,
          "contribution": 0.0
        },
        "real_yields": {
          "weight": 2.5,
          "score": 1,
          "contribution": 2.5
        },
        "vix": {
          "weight": 2.0,
          "score": 1,
          "contribution": 2.0
        },
        "dxy": {
          "weight": 1.5,
          "score": 1,
          "contribution": 1.5
        },
        "growth": {
          "weight": 2.0,
          "score": 0,
          "contribution": 0.0
        },
        "credit_spreads": {
          "weight": 2.0,
          "score": 1,
          "contribution": 2.0
        },
        "curve_2s10s": {
          "weight": 1.5,
          "score": 1,
          "contribution": 1.5
        },
        "sox": {
          "weight": 1.5,
          "score": 1,
          "contribution": 1.5
        },
        "move": {
          "weight": 1.0,
          "score": 1,
          "contribution": 1.0
        }
      }
    },
    "NQ": {
      "name": "E-mini Nasdaq-100",
      "bias_score": 7.27,
      "raw_bias": 0.727,
      "bias_direction": "BULLISH",
      "conviction": "HIGH",
      "factor_contributions": {
        "fed_stance": {
          "weight": 3.0,
          "score": 0,
          "contribution": 0.0
        },
        "real_yields": {
          "weight": 3.0,
          "score": 1,
          "contribution": 3.0
        },
        "vix": {
          "weight": 2.0,
          "score": 1,
          "contribution": 2.0
        },
        "dxy": {
          "weight": 1.5,
          "score": 1,
          "contribution": 1.5
        },
        "growth": {
          "weight": 1.5,
          "score": 0,
          "contribution": 0.0
        },
        "credit_spreads": {
          "weight": 1.5,
          "score": 1,
          "contribution": 1.5
        },
        "sox": {
          "weight": 3.0,
          "score": 1,
          "contribution": 3.0
        },
        "move": {
          "weight": 1.0,
          "score": 1,
          "contribution": 1.0
        }
      }
    },
    "RTY": {
      "name": "E-mini Russell 2000",
      "bias_score": 6.45,
      "raw_bias": 0.645,
      "bias_direction": "BULLISH",
      "conviction": "HIGH",
      "factor_contributions": {
        "fed_stance": {
          "weight": 3.0,
          "score": 0,
          "contribution": 0.0
        },
        "real_yields": {
          "weight": 2.0,
          "score": 1,
          "contribution": 2.0
        },
        "vix": {
          "weight": 2.0,
          "score": 1,
          "contribution": 2.0
        },
        "dxy": {
          "weight": 1.5,
          "score": 1,
          "contribution": 1.5
        },
        "growth": {
          "weight": 2.5,
          "score": 0,
          "contribution": 0.0
        },
        "credit_spreads": {
          "weight": 2.5,
          "score": 1,
          "contribution": 2.5
        },
        "curve_2s10s": {
          "weight": 2.0,
          "score": 1,
          "contribution": 2.0
        }
      }
    },
    "GC": {
      "name": "Gold Futures",
      "bias_score": 8.18,
      "raw_bias": 0.818,
      "bias_direction": "BULLISH",
      "conviction": "HIGH",
      "factor_contributions": {
        "fed_stance": {
          "weight": 3.0,
          "score": 0,
          "contribution": 0.0
        },
        "real_yields": {
          "weight": 3.5,
          "score": 1,
          "contribution": 3.5
        },
        "vix": {
          "weight": 1.5,
          "score": 1,
          "contribution": 1.5
        },
        "dxy": {
          "weight": 3.0,
          "score": 1,
          "contribution": 3.0
        },
        "credit_spreads": {
          "weight": 1.0,
          "score": 1,
          "contribution": 1.0
        },
        "gold_etf_flows": {
          "weight": 2.5,
          "score": 1,
          "contribution": 2.5
        },
        "geopolitical_risk": {
          "weight": 2.0,
          "score": 1,
          "contribution": 2.0
        }
      }
    },
    "CL": {
      "name": "Crude Oil Futures",
      "bias_score": 3.55,
      "raw_bias": 0.355,
      "bias_direction": "BULLISH",
      "conviction": "MODERATE",
      "factor_contributions": {
        "growth": {
          "weight": 2.5,
          "score": 0,
          "contribution": 0.0
        },
        "dxy": {
          "weight": 2.0,
          "score": 1,
          "contribution": 2.0
        },
        "oil_inventories": {
          "weight": 3.0,
          "score": 1,
          "contribution": 3.0
        },
        "oil_supply": {
          "weight": 3.5,
          "score": 0,
          "contribution": 0.0
        },
        "geopolitical_risk": {
          "weight": 2.5,
          "score": 1,
          "contribution": 2.5
        },
        "china_growth": {
          "weight": 2.0,
          "score": -1,
          "contribution": -2.0
        }
      }
    },
    "ZN": {
      "name": "10-Year Treasury Note",
      "bias_score": 6.21,
      "raw_bias": 0.621,
      "bias_direction": "BULLISH",
      "conviction": "HIGH",
      "factor_contributions": {
        "fed_stance": {
          "weight": 3.5,
          "score": 0,
          "contribution": 0.0
        },
        "real_yields": {
          "weight": 3.0,
          "score": 1,
          "contribution": 3.0
        },
        "growth": {
          "weight": 2.0,
          "score": 0,
          "contribution": 0.0
        },
        "credit_spreads": {
          "weight": 1.5,
          "score": 1,
          "contribution": 1.5
        },
        "curve_2s10s": {
          "weight": 2.0,
          "score": 1,
          "contribution": 2.0
        },
        "move": {
          "weight": 1.5,
          "score": 1,
          "contribution": 1.5
        },
        "vix": {
          "weight": 1.0,
          "score": 1,
          "contribution": 1.0
        }
      }
    },
    "M6E": {
      "name": "Micro Euro FX",
      "bias_score": 4.0,
      "raw_bias": 0.4,
      "bias_direction": "BULLISH",
      "conviction": "MODERATE",
      "factor_contributions": {
        "fed_stance": {
          "weight": 2.5,
          "score": 0,
          "contribution": 0.0
        },
        "ecb_stance": {
          "weight": 3.5,
          "score": 0,
          "contribution": 0.0
        },
        "dxy": {
          "weight": 3.0,
          "score": 1,
          "contribution": 3.0
        },
        "growth": {
          "weight": 1.5,
          "score": 0,
          "contribution": 0.0
        },
        "real_yields": {
          "weight": 2.0,
          "score": 1,
          "contribution": 2.0
        }
      }
    },
    "6A": {
      "name": "Australian Dollar",
      "bias_score": 3.08,
      "raw_bias": 0.308,
      "bias_direction": "BULLISH",
      "conviction": "MODERATE",
      "factor_contributions": {
        "fed_stance": {
          "weight": 2.0,
          "score": 0,
          "contribution": 0.0
        },
        "rba_stance": {
          "weight": 3.5,
          "score": 1,
          "contribution": 3.5
        },
        "dxy": {
          "weight": 3.0,
          "score": 1,
          "contribution": 3.0
        },
        "china_growth": {
          "weight": 2.5,
          "score": -1,
          "contribution": -2.5
        },
        "copper": {
          "weight": 2.0,
          "score": 0,
          "contribution": 0.0
        }
      }
    },
    "6J": {
      "name": "Japanese Yen",
      "bias_score": 5.2,
      "raw_bias": 0.52,
      "bias_direction": "BULLISH",
      "conviction": "HIGH",
      "factor_contributions": {
        "fed_stance": {
          "weight": 2.5,
          "score": 0,
          "contribution": 0.0
        },
        "boj_stance": {
          "weight": 3.5,
          "score": 0,
          "contribution": 0.0
        },
        "dxy": {
          "weight": 3.0,
          "score": 1,
          "contribution": 3.0
        },
        "real_yields": {
          "weight": 2.0,
          "score": 1,
          "contribution": 2.0
        },
        "vix": {
          "weight": 1.5,
          "score": 1,
          "contribution": 1.5
        }
      }
    },
    "HG": {
      "name": "Copper Futures",
      "bias_score": 0.0,
      "raw_bias": 0.0,
      "bias_direction": "NEUTRAL",
      "conviction": "MODERATE",
      "factor_contributions": {
        "growth": {
          "weight": 2.5,
          "score": 0,
          "contribution": 0.0
        },
        "china_growth": {
          "weight": 3.5,
          "score": -1,
          "contribution": -3.5
        },
        "dxy": {
          "weight": 2.0,
          "score": 1,
          "contribution": 2.0
        },
        "copper": {
          "weight": 3.0,
          "score": 0,
          "contribution": 0.0
        },
        "sox": {
          "weight": 1.5,
          "score": 1,
          "contribution": 1.5
        }
      }
    }
  }
}