{
  "date": "2026-03-02",
  "generated_at": "2026-03-02T19:35:00Z",
  "scores": {
    "GC": {"score": -2, "signal": "SLIGHT_BEARISH", "confidence": 6},
    "SI": {"score": 0, "signal": "NEUTRAL", "confidence": 6},
    "CL": {"score": -1, "signal": "NEUTRAL", "confidence": 5},
    "ES": {"score": -6, "signal": "STRONG_BEARISH", "confidence": 7},
    "NQ": {"score": -5, "signal": "BEARISH", "confidence": 7},
    "YM": {"score": -5, "signal": "BEARISH", "confidence": 7},
    "RTY": {"score": -6, "signal": "STRONG_BEARISH", "confidence": 8},
    "M6E": {"score": 1, "signal": "SLIGHT_BULLISH", "confidence": 5},
    "6A": {"score": 1, "signal": "SLIGHT_BULLISH", "confidence": 5},
    "6J": {"score": 5, "signal": "STRONG_BULLISH", "confidence": 7}
  },
  "asset_class_bias": {
    "COMMODITIES": "MIXED",
    "INDICES": "BEARISH",
    "FX": "BULLISH"
  },
  "key_drivers": [
    "US-Israel strikes on Iran triggering geopolitical risk-off; Strait of Hormuz fears spiking oil +8-13% and gold +2.8%",
    "10Y real yields rising sharply (+10bps to 4.051%) on inflation fears from oil shock, crushing equity and gold valuations",
    "VIX surging to 21.44 (+7.96%), credit spreads widening, yield curve flattening — all pointing to equity bear regime",
    "BOJ hawkish hiking cycle + safe-haven demand = strong JPY thesis; FX bloc bullish as USD strength offset by rate differentials",
    "ISM Manufacturing PMI 52.4% and GDPNow 3.0% signal strong US growth, reducing Fed cut probability and weighing on equities"
  ],
  "data_quality": {
    "stale_sources": ["FRED DFII10 (used search fallback for real yield level)", "FRED BAMLH0A0HYM2 (used TradingEconomics fallback: 2.98% OAS)", "World Gold Council ETF flows (Jan 2026 data, most recent available)"],
    "fallbacks_used": [
      "10Y TIPS real yield: Medium.com/XT_com article citing 1.77% real yield",
      "HY OAS: TradingEconomics citing 2.98% for Feb 2026",
      "2s10s spread: Bitget/Futunn articles citing ~55bps spread with 2Y at 3.41%, 10Y at 4.051%",
      "VIX: CBOE direct (21.44)",
      "MOVE: TradingView direct (73.21)",
      "DXY: TradingView direct (98.556)",
      "SOX: TradingView direct (8,137.36)",
      "Copper: Investing.com direct (5.9648)",
      "GDPNow: TradingView news citing 3.0% Q1 2026",
      "ECB stance: Reuters/CNBC citing hold at 2.00% on Feb 5, 2026",
      "RBA stance: Reuters/RBA citing hike to 3.85% on Feb 3, 2026",
      "BOJ stance: Reuters/Bloomberg citing hold at 0.75% in Jan 2026, hawkish path"
    ]
  }
}
