{
  "date": "2026-02-12",
  "generated_at": "2026-02-13T00:45:00Z",
  "scores": {
    "GC": {
      "score": 3,
      "signal": "BULLISH",
      "confidence": 7
    },
    "SI": {
      "score": 2,
      "signal": "SLIGHT_BULLISH",
      "confidence": 6
    },
    "CL": {
      "score": 1,
      "signal": "SLIGHT_BULLISH",
      "confidence": 5
    },
    "ES": {
      "score": 0,
      "signal": "NEUTRAL",
      "confidence": 6
    },
    "NQ": {
      "score": 0,
      "signal": "NEUTRAL",
      "confidence": 6
    },
    "YM": {
      "score": 2,
      "signal": "SLIGHT_BULLISH",
      "confidence": 6
    },
    "RTY": {
      "score": 3,
      "signal": "BULLISH",
      "confidence": 7
    },
    "M6E": {
      "score": 0,
      "signal": "NEUTRAL",
      "confidence": 5
    },
    "6A": {
      "score": -1,
      "signal": "NEUTRAL",
      "confidence": 6
    },
    "6J": {
      "score": 6,
      "signal": "STRONG_BULLISH",
      "confidence": 8
    }
  },
  "asset_class_bias": {
    "COMMODITIES": "BULLISH",
    "INDICES": "MIXED",
    "FX": "MIXED"
  },
  "key_drivers": [
    "Weak USD supporting commodities and FX",
    "Risk-off environment (VIX >20) creating safe-haven flows to gold and yen",
    "Credit spreads narrowing supporting equities, especially small caps"
  ],
  "data_quality": {
    "stale_sources": [],
    "fallbacks_used": []
  }
}
